[{"id":"e46580b4-1071-11ee-a2b7-6045bd925463","brand":"PIACELABO <JP>","series":"COLOR ADDITION","shade":"BROWN","type":"treatment","catalogNo":"","price":1470,"barcodeCount":1,"barcode":"4545228424765","flag":0,"shadeDesc":""},{"id":"e46578cb-1071-11ee-a2b7-6045bd925463","brand":"PIACELABO <JP>","series":"formulate","shade":"OX-3 1000ml","type":"developer","catalogNo":"","price":1200,"barcodeCount":1,"barcode":"4545228281030","flag":0,"shadeDesc":""},{"id":"e4657862-1071-11ee-a2b7-6045bd925463","brand":"PIACELABO <JP>","series":"formulate","shade":"OX-3AS 1000ml","type":"developer","catalogNo":"","price":1200,"barcodeCount":1,"barcode":"4545228423805","flag":0,"shadeDesc":""},{"id":"e4657806-1071-11ee-a2b7-6045bd925463","brand":"PIACELABO <JP>","series":"formulate","shade":"OX-6 1000ml","type":"developer","catalogNo":"","price":1200,"barcodeCount":1,"barcode":"4545228280927","flag":0,"shadeDesc":""},{"id":"e465afb5-1071-11ee-a2b7-6045bd925463","brand":"PIACELABO <JP>","series":"formulate ADVAGE","shade":"12N","type":"color","catalogNo":"","price":600,"barcodeCount":1,"barcode":"4545228207221","flag":0,"shadeDesc":""},{"id":"e465ab84-1071-11ee-a2b7-6045bd925463","brand":"PIACELABO <JP>","series":"formulate ADVAGE","shade":"4N","type":"color","catalogNo":"","price":600,"barcodeCount":1,"barcode":"4545228207788","flag":0,"shadeDesc":""},{"id":"e465ab27-1071-11ee-a2b7-6045bd925463","brand":"PIACELABO <JP>","series":"formulate ADVAGE","shade":"5A","type":"color","catalogNo":"","price":600,"barcodeCount":1,"barcode":"4545228209713","flag":0,"shadeDesc":""},{"id":"e465aacc-1071-11ee-a2b7-6045bd925463","brand":"PIACELABO <JP>","series":"formulate ADVAGE","shade":"5Ap","type":"color","catalogNo":"","price":600,"barcodeCount":1,"barcode":"4545228208501","flag":0,"shadeDesc":""},{"id":"e465aa11-1071-11ee-a2b7-6045bd925463","brand":"PIACELABO <JP>","series":"formulate ADVAGE","shade":"5Be","type":"color","catalogNo":"","price":600,"barcodeCount":1,"barcode":"4545228242079","flag":0,"shadeDesc":""},{"id":"e465a9b7-1071-11ee-a2b7-6045bd925463","brand":"PIACELABO <JP>","series":"formulate ADVAGE","shade":"5Co","type":"color","catalogNo":"","price":600,"barcodeCount":1,"barcode":"4545228242857","flag":0,"shadeDesc":""},{"id":"e465a95b-1071-11ee-a2b7-6045bd925463","brand":"PIACELABO <JP>","series":"formulate ADVAGE","shade":"5G","type":"color","catalogNo":"","price":600,"barcodeCount":1,"barcode":"4545228208990","flag":0,"shadeDesc":""},{"id":"e465a8fa-1071-11ee-a2b7-6045bd925463","brand":"PIACELABO <JP>","series":"formulate ADVAGE","shade":"5H","type":"color","catalogNo":"","price":600,"barcodeCount":1,"barcode":"4545228242468","flag":0,"shadeDesc":""},{"id":"e465a892-1071-11ee-a2b7-6045bd925463","brand":"PIACELABO <JP>","series":"formulate ADVAGE","shade":"5L","type":"color","catalogNo":"","price":600,"barcodeCount":1,"barcode":"4545228209324","flag":0,"shadeDesc":""},{"id":"e465a830-1071-11ee-a2b7-6045bd925463","brand":"PIACELABO <JP>","series":"formulate ADVAGE","shade":"5La","type":"color","catalogNo":"","price":600,"barcodeCount":1,"barcode":"4545228210153","flag":0,"shadeDesc":""},{"id":"e465a7d6-1071-11ee-a2b7-6045bd925463","brand":"PIACELABO <JP>","series":"formulate ADVAGE","shade":"5Mo","type":"color","catalogNo":"","price":600,"barcodeCount":1,"barcode":"4545228241645","flag":0,"shadeDesc":""},{"id":"e465a71e-1071-11ee-a2b7-6045bd925463","brand":"PIACELABO <JP>","series":"formulate ADVAGE","shade":"5N","type":"color","catalogNo":"","price":600,"barcodeCount":1,"barcode":"4545228207610","flag":0,"shadeDesc":""},{"id":"e465a6c2-1071-11ee-a2b7-6045bd925463","brand":"PIACELABO <JP>","series":"formulate ADVAGE","shade":"5R","type":"color","catalogNo":"","price":600,"barcodeCount":1,"barcode":"4545228208112","flag":0,"shadeDesc":""},{"id":"e465a4b5-1071-11ee-a2b7-6045bd925463","brand":"PIACELABO <JP>","series":"formulate ADVAGE","shade":"6A","type":"color","catalogNo":"","price":600,"barcodeCount":1,"barcode":"4545228209645","flag":0,"shadeDesc":""},{"id":"e465a3ff-1071-11ee-a2b7-6045bd925463","brand":"PIACELABO <JP>","series":"formulate ADVAGE","shade":"6Ap","type":"color","catalogNo":"","price":600,"barcodeCount":1,"barcode":"4545228208433","flag":0,"shadeDesc":""},{"id":"e465a238-1071-11ee-a2b7-6045bd925463","brand":"PIACELABO <JP>","series":"formulate ADVAGE","shade":"6Be","type":"color","catalogNo":"","price":600,"barcodeCount":1,"barcode":"4545228241966","flag":0,"shadeDesc":""},{"id":"e465a0c5-1071-11ee-a2b7-6045bd925463","brand":"PIACELABO <JP>","series":"formulate ADVAGE","shade":"6Co","type":"color","catalogNo":"","price":600,"barcodeCount":1,"barcode":"4545228242789","flag":0,"shadeDesc":""},{"id":"e465a06b-1071-11ee-a2b7-6045bd925463","brand":"PIACELABO <JP>","series":"formulate ADVAGE","shade":"6G","type":"color","catalogNo":"","price":600,"barcodeCount":1,"barcode":"4545228208822","flag":0,"shadeDesc":""},{"id":"e465a00d-1071-11ee-a2b7-6045bd925463","brand":"PIACELABO <JP>","series":"formulate ADVAGE","shade":"6H","type":"color","catalogNo":"","price":600,"barcodeCount":1,"barcode":"4545228242390","flag":0,"shadeDesc":""},{"id":"e4659fb1-1071-11ee-a2b7-6045bd925463","brand":"PIACELABO <JP>","series":"formulate ADVAGE","shade":"6L","type":"color","catalogNo":"","price":600,"barcodeCount":1,"barcode":"4545228209249","flag":0,"shadeDesc":""},{"id":"e4659ef2-1071-11ee-a2b7-6045bd925463","brand":"PIACELABO <JP>","series":"formulate ADVAGE","shade":"6La","type":"color","catalogNo":"","price":600,"barcodeCount":1,"barcode":"4545228210085","flag":0,"shadeDesc":""},{"id":"e4659ddf-1071-11ee-a2b7-6045bd925463","brand":"PIACELABO <JP>","series":"formulate ADVAGE","shade":"6Mo","type":"color","catalogNo":"","price":600,"barcodeCount":1,"barcode":"4545228241577","flag":0,"shadeDesc":""},{"id":"e4659cc2-1071-11ee-a2b7-6045bd925463","brand":"PIACELABO <JP>","series":"formulate ADVAGE","shade":"6N","type":"color","catalogNo":"","price":600,"barcodeCount":1,"barcode":"4545228207542","flag":0,"shadeDesc":""},{"id":"e4659af1-1071-11ee-a2b7-6045bd925463","brand":"PIACELABO <JP>","series":"formulate ADVAGE","shade":"6R","type":"color","catalogNo":"","price":600,"barcodeCount":1,"barcode":"4545228208044","flag":0,"shadeDesc":""},{"id":"e4659983-1071-11ee-a2b7-6045bd925463","brand":"PIACELABO <JP>","series":"formulate ADVAGE","shade":"7A","type":"color","catalogNo":"","price":600,"barcodeCount":1,"barcode":"4545228209560","flag":0,"shadeDesc":""},{"id":"e4659925-1071-11ee-a2b7-6045bd925463","brand":"PIACELABO <JP>","series":"formulate ADVAGE","shade":"7Ap","type":"color","catalogNo":"","price":600,"barcodeCount":1,"barcode":"4545228208358","flag":0,"shadeDesc":""},{"id":"e4659869-1071-11ee-a2b7-6045bd925463","brand":"PIACELABO <JP>","series":"formulate ADVAGE","shade":"7Be","type":"color","catalogNo":"","price":600,"barcodeCount":1,"barcode":"4545228241898","flag":0,"shadeDesc":""},{"id":"e465980f-1071-11ee-a2b7-6045bd925463","brand":"PIACELABO <JP>","series":"formulate ADVAGE","shade":"7Co","type":"color","catalogNo":"","price":600,"barcodeCount":1,"barcode":"4545228242611","flag":0,"shadeDesc":""},{"id":"e46597b2-1071-11ee-a2b7-6045bd925463","brand":"PIACELABO <JP>","series":"formulate ADVAGE","shade":"7G","type":"color","catalogNo":"","price":600,"barcodeCount":1,"barcode":"4545228208747","flag":0,"shadeDesc":""},{"id":"e4659755-1071-11ee-a2b7-6045bd925463","brand":"PIACELABO <JP>","series":"formulate ADVAGE","shade":"7H","type":"color","catalogNo":"","price":600,"barcodeCount":1,"barcode":"4545228242222","flag":0,"shadeDesc":""},{"id":"e46596f8-1071-11ee-a2b7-6045bd925463","brand":"PIACELABO <JP>","series":"formulate ADVAGE","shade":"7L","type":"color","catalogNo":"","price":600,"barcodeCount":1,"barcode":"4545228209171","flag":0,"shadeDesc":""},{"id":"e465969b-1071-11ee-a2b7-6045bd925463","brand":"PIACELABO <JP>","series":"formulate ADVAGE","shade":"7La","type":"color","catalogNo":"","price":600,"barcodeCount":1,"barcode":"4545228209959","flag":0,"shadeDesc":""},{"id":"e465963b-1071-11ee-a2b7-6045bd925463","brand":"PIACELABO <JP>","series":"formulate ADVAGE","shade":"7Mo","type":"color","catalogNo":"","price":600,"barcodeCount":1,"barcode":"4545228241409","flag":0,"shadeDesc":""},{"id":"e4659526-1071-11ee-a2b7-6045bd925463","brand":"PIACELABO <JP>","series":"formulate ADVAGE","shade":"7N","type":"color","catalogNo":"","price":600,"barcodeCount":1,"barcode":"4545228207467","flag":0,"shadeDesc":""},{"id":"e46594cb-1071-11ee-a2b7-6045bd925463","brand":"PIACELABO <JP>","series":"formulate ADVAGE","shade":"7R","type":"color","catalogNo":"","price":600,"barcodeCount":1,"barcode":"4545228207931","flag":0,"shadeDesc":""},{"id":"e4659293-1071-11ee-a2b7-6045bd925463","brand":"PIACELABO <JP>","series":"formulate ADVAGE","shade":"8A","type":"color","catalogNo":"","price":600,"barcodeCount":1,"barcode":"4545228209492","flag":0,"shadeDesc":""},{"id":"e46591df-1071-11ee-a2b7-6045bd925463","brand":"PIACELABO <JP>","series":"formulate ADVAGE","shade":"8Ap","type":"color","catalogNo":"","price":600,"barcodeCount":1,"barcode":"4545228208280","flag":0,"shadeDesc":""},{"id":"e4658fad-1071-11ee-a2b7-6045bd925463","brand":"PIACELABO <JP>","series":"formulate ADVAGE","shade":"8Be","type":"color","catalogNo":"","price":600,"barcodeCount":1,"barcode":"4545228241720","flag":3,"shadeDesc":""},{"id":"e4658ea2-1071-11ee-a2b7-6045bd925463","brand":"PIACELABO <JP>","series":"formulate ADVAGE","shade":"8Co","type":"color","catalogNo":"","price":600,"barcodeCount":1,"barcode":"4545228242543","flag":0,"shadeDesc":""},{"id":"e4658ded-1071-11ee-a2b7-6045bd925463","brand":"PIACELABO <JP>","series":"formulate ADVAGE","shade":"8G","type":"color","catalogNo":"","price":600,"barcodeCount":1,"barcode":"4545228208679","flag":0,"shadeDesc":""},{"id":"e4658d92-1071-11ee-a2b7-6045bd925463","brand":"PIACELABO <JP>","series":"formulate ADVAGE","shade":"8H","type":"color","catalogNo":"","price":600,"barcodeCount":1,"barcode":"4545228242147","flag":0,"shadeDesc":""},{"id":"e4658d37-1071-11ee-a2b7-6045bd925463","brand":"PIACELABO <JP>","series":"formulate ADVAGE","shade":"8L","type":"color","catalogNo":"","price":600,"barcodeCount":1,"barcode":"4545228209003","flag":0,"shadeDesc":""},{"id":"e4658c7d-1071-11ee-a2b7-6045bd925463","brand":"PIACELABO <JP>","series":"formulate ADVAGE","shade":"8La","type":"color","catalogNo":"","price":600,"barcodeCount":1,"barcode":"4545228209881","flag":0,"shadeDesc":""},{"id":"e4658b5d-1071-11ee-a2b7-6045bd925463","brand":"PIACELABO <JP>","series":"formulate ADVAGE","shade":"8Mo","type":"color","catalogNo":"","price":600,"barcodeCount":1,"barcode":"4545228241720","flag":3,"shadeDesc":""},{"id":"e4658a33-1071-11ee-a2b7-6045bd925463","brand":"PIACELABO <JP>","series":"formulate ADVAGE","shade":"8N","type":"color","catalogNo":"","price":600,"barcodeCount":1,"barcode":"4545228207399","flag":0,"shadeDesc":""},{"id":"e4658409-1071-11ee-a2b7-6045bd925463","brand":"PIACELABO <JP>","series":"formulate ADVAGE","shade":"8R","type":"color","catalogNo":"","price":600,"barcodeCount":1,"barcode":"4545228207856","flag":0,"shadeDesc":""},{"id":"e465816c-1071-11ee-a2b7-6045bd925463","brand":"PIACELABO <JP>","series":"formulate ADVAGE","shade":"AZ","type":"color","catalogNo":"","price":600,"barcodeCount":1,"barcode":"4545228210238","flag":0,"shadeDesc":""},{"id":"e465bba7-1071-11ee-a2b7-6045bd925463","brand":"PIACELABO <JP>","series":"formulate amelti","shade":"10A","type":"color","catalogNo":"","price":580,"barcodeCount":1,"barcode":"4545228270645","flag":0,"shadeDesc":""},{"id":"e465bb3d-1071-11ee-a2b7-6045bd925463","brand":"PIACELABO <JP>","series":"formulate amelti","shade":"10Ap","type":"color","catalogNo":"","price":580,"barcodeCount":1,"barcode":"4545228269038","flag":0,"shadeDesc":""},{"id":"e465bad6-1071-11ee-a2b7-6045bd925463","brand":"PIACELABO <JP>","series":"formulate amelti","shade":"10B","type":"color","catalogNo":"","price":580,"barcodeCount":1,"barcode":"4545228267959","flag":0,"shadeDesc":""},{"id":"e465ba6d-1071-11ee-a2b7-6045bd925463","brand":"PIACELABO <JP>","series":"formulate amelti","shade":"10BA","type":"color","catalogNo":"","price":580,"barcodeCount":1,"barcode":"4545228311553","flag":0,"shadeDesc":""},{"id":"e465ba06-1071-11ee-a2b7-6045bd925463","brand":"PIACELABO <JP>","series":"formulate amelti","shade":"10Be","type":"color","catalogNo":"","price":580,"barcodeCount":1,"barcode":"4545228268215","flag":0,"shadeDesc":""},{"id":"e465b933-1071-11ee-a2b7-6045bd925463","brand":"PIACELABO <JP>","series":"formulate amelti","shade":"10CA","type":"color","catalogNo":"","price":580,"barcodeCount":1,"barcode":"4545228311942","flag":0,"shadeDesc":""},{"id":"e465b8c9-1071-11ee-a2b7-6045bd925463","brand":"PIACELABO <JP>","series":"formulate amelti","shade":"10Co","type":"color","catalogNo":"","price":580,"barcodeCount":1,"barcode":"4545228311164","flag":0,"shadeDesc":""},{"id":"e465b862-1071-11ee-a2b7-6045bd925463","brand":"PIACELABO <JP>","series":"formulate amelti","shade":"10G","type":"color","catalogNo":"","price":580,"barcodeCount":1,"barcode":"4545228269427","flag":0,"shadeDesc":""},{"id":"e465b7f7-1071-11ee-a2b7-6045bd925463","brand":"PIACELABO <JP>","series":"formulate amelti","shade":"10La","type":"color","catalogNo":"","price":580,"barcodeCount":1,"barcode":"4545228271079","flag":0,"shadeDesc":""},{"id":"e465b64e-1071-11ee-a2b7-6045bd925463","brand":"PIACELABO <JP>","series":"formulate amelti","shade":"10N","type":"color","catalogNo":"","price":580,"barcodeCount":1,"barcode":"4545228267171","flag":0,"shadeDesc":""},{"id":"e465b5e1-1071-11ee-a2b7-6045bd925463","brand":"PIACELABO <JP>","series":"formulate amelti","shade":"10O","type":"color","catalogNo":"","price":580,"barcodeCount":1,"barcode":"4545228270256","flag":0,"shadeDesc":""},{"id":"e465b573-1071-11ee-a2b7-6045bd925463","brand":"PIACELABO <JP>","series":"formulate amelti","shade":"10P","type":"color","catalogNo":"","price":580,"barcodeCount":1,"barcode":"4545228271468","flag":0,"shadeDesc":""},{"id":"e465b4a1-1071-11ee-a2b7-6045bd925463","brand":"PIACELABO <JP>","series":"formulate amelti","shade":"10R","type":"color","catalogNo":"","price":580,"barcodeCount":1,"barcode":"4545228268604","flag":0,"shadeDesc":""},{"id":"e465b314-1071-11ee-a2b7-6045bd925463","brand":"PIACELABO <JP>","series":"formulate amelti","shade":"12A","type":"color","catalogNo":"","price":580,"barcodeCount":1,"barcode":"4545228270577","flag":0,"shadeDesc":""},{"id":"e465b2aa-1071-11ee-a2b7-6045bd925463","brand":"PIACELABO <JP>","series":"formulate amelti","shade":"12Ap","type":"color","catalogNo":"","price":580,"barcodeCount":1,"barcode":"4545228268925","flag":0,"shadeDesc":""},{"id":"e465b23e-1071-11ee-a2b7-6045bd925463","brand":"PIACELABO <JP>","series":"formulate amelti","shade":"12BA","type":"color","catalogNo":"","price":580,"barcodeCount":1,"barcode":"4545228311485","flag":0,"shadeDesc":""},{"id":"e465b16a-1071-11ee-a2b7-6045bd925463","brand":"PIACELABO <JP>","series":"formulate amelti","shade":"12CA","type":"color","catalogNo":"","price":580,"barcodeCount":1,"barcode":"4545228311874","flag":0,"shadeDesc":""},{"id":"e465b0ff-1071-11ee-a2b7-6045bd925463","brand":"PIACELABO <JP>","series":"formulate amelti","shade":"12G","type":"color","catalogNo":"","price":580,"barcodeCount":1,"barcode":"4545228269342","flag":0,"shadeDesc":""},{"id":"e465b091-1071-11ee-a2b7-6045bd925463","brand":"PIACELABO <JP>","series":"formulate amelti","shade":"12La","type":"color","catalogNo":"","price":580,"barcodeCount":1,"barcode":"4545228270966","flag":0,"shadeDesc":""},{"id":"e465b024-1071-11ee-a2b7-6045bd925463","brand":"PIACELABO <JP>","series":"formulate amelti","shade":"12N","type":"color","catalogNo":"","price":580,"barcodeCount":1,"barcode":"4545228267003","flag":0,"shadeDesc":""},{"id":"e465af51-1071-11ee-a2b7-6045bd925463","brand":"PIACELABO <JP>","series":"formulate amelti","shade":"12O","type":"color","catalogNo":"","price":580,"barcodeCount":1,"barcode":"4545228270188","flag":0,"shadeDesc":""},{"id":"e465aeeb-1071-11ee-a2b7-6045bd925463","brand":"PIACELABO <JP>","series":"formulate amelti","shade":"12P","type":"color","catalogNo":"","price":580,"barcodeCount":1,"barcode":"4545228271390","flag":0,"shadeDesc":""},{"id":"e465ae14-1071-11ee-a2b7-6045bd925463","brand":"PIACELABO <JP>","series":"formulate amelti","shade":"12R","type":"color","catalogNo":"","price":580,"barcodeCount":1,"barcode":"4545228268536","flag":0,"shadeDesc":""},{"id":"e465ad59-1071-11ee-a2b7-6045bd925463","brand":"PIACELABO <JP>","series":"formulate amelti","shade":"14N","type":"color","catalogNo":"","price":580,"barcodeCount":1,"barcode":"4545228266990","flag":0,"shadeDesc":""},{"id":"e465acfb-1071-11ee-a2b7-6045bd925463","brand":"PIACELABO <JP>","series":"formulate amelti","shade":"2N","type":"color","catalogNo":"","price":580,"barcodeCount":1,"barcode":"4545228267881","flag":0,"shadeDesc":""},{"id":"e465abe2-1071-11ee-a2b7-6045bd925463","brand":"PIACELABO <JP>","series":"formulate amelti","shade":"4N","type":"color","catalogNo":"","price":580,"barcodeCount":1,"barcode":"4545228267713","flag":0,"shadeDesc":""},{"id":"e465a77a-1071-11ee-a2b7-6045bd925463","brand":"PIACELABO <JP>","series":"formulate amelti","shade":"5N","type":"color","catalogNo":"","price":580,"barcodeCount":1,"barcode":"4545228267645","flag":0,"shadeDesc":""},{"id":"e465a5a6-1071-11ee-a2b7-6045bd925463","brand":"PIACELABO <JP>","series":"formulate amelti","shade":"6A","type":"color","catalogNo":"","price":580,"barcodeCount":1,"barcode":"4545228270898","flag":0,"shadeDesc":""},{"id":"e465a459-1071-11ee-a2b7-6045bd925463","brand":"PIACELABO <JP>","series":"formulate amelti","shade":"6Ap","type":"color","catalogNo":"","price":580,"barcodeCount":1,"barcode":"4545228269274","flag":0,"shadeDesc":""},{"id":"e465a349-1071-11ee-a2b7-6045bd925463","brand":"PIACELABO <JP>","series":"formulate amelti","shade":"6B","type":"color","catalogNo":"","price":580,"barcodeCount":1,"barcode":"4545228268147","flag":0,"shadeDesc":""},{"id":"e465a2f0-1071-11ee-a2b7-6045bd925463","brand":"PIACELABO <JP>","series":"formulate amelti","shade":"6BA","type":"color","catalogNo":"","price":580,"barcodeCount":1,"barcode":"4545228311706","flag":0,"shadeDesc":""},{"id":"e465a295-1071-11ee-a2b7-6045bd925463","brand":"PIACELABO <JP>","series":"formulate amelti","shade":"6Be","type":"color","catalogNo":"","price":580,"barcodeCount":1,"barcode":"4545228268451","flag":0,"shadeDesc":""},{"id":"e465a17a-1071-11ee-a2b7-6045bd925463","brand":"PIACELABO <JP>","series":"formulate amelti","shade":"6CA","type":"color","catalogNo":"","price":580,"barcodeCount":1,"barcode":"4545228312130","flag":0,"shadeDesc":""},{"id":"e465a11f-1071-11ee-a2b7-6045bd925463","brand":"PIACELABO <JP>","series":"formulate amelti","shade":"6Co","type":"color","catalogNo":"","price":580,"barcodeCount":1,"barcode":"4545228311317","flag":0,"shadeDesc":""},{"id":"e4659f52-1071-11ee-a2b7-6045bd925463","brand":"PIACELABO <JP>","series":"formulate amelti","shade":"6La","type":"color","catalogNo":"","price":580,"barcodeCount":1,"barcode":"4545228271222","flag":0,"shadeDesc":""},{"id":"e4659d22-1071-11ee-a2b7-6045bd925463","brand":"PIACELABO <JP>","series":"formulate amelti","shade":"6N","type":"color","catalogNo":"","price":580,"barcodeCount":1,"barcode":"4545228267560","flag":0,"shadeDesc":""},{"id":"e4659c65-1071-11ee-a2b7-6045bd925463","brand":"PIACELABO <JP>","series":"formulate amelti","shade":"6O","type":"color","catalogNo":"","price":580,"barcodeCount":1,"barcode":"4545228270409","flag":0,"shadeDesc":""},{"id":"e4659c05-1071-11ee-a2b7-6045bd925463","brand":"PIACELABO <JP>","series":"formulate amelti","shade":"6P","type":"color","catalogNo":"","price":580,"barcodeCount":1,"barcode":"4545228271611","flag":0,"shadeDesc":""},{"id":"e4659b4a-1071-11ee-a2b7-6045bd925463","brand":"PIACELABO <JP>","series":"formulate amelti","shade":"6R","type":"color","catalogNo":"","price":580,"barcodeCount":1,"barcode":"4545228268840","flag":0,"shadeDesc":""},{"id":"e4659582-1071-11ee-a2b7-6045bd925463","brand":"PIACELABO <JP>","series":"formulate amelti","shade":"7N","type":"color","catalogNo":"","price":580,"barcodeCount":1,"barcode":"4545228267492","flag":0,"shadeDesc":""},{"id":"e46592f2-1071-11ee-a2b7-6045bd925463","brand":"PIACELABO <JP>","series":"formulate amelti","shade":"8A","type":"color","catalogNo":"","price":580,"barcodeCount":1,"barcode":"4545228270720","flag":0,"shadeDesc":""},{"id":"e4659237-1071-11ee-a2b7-6045bd925463","brand":"PIACELABO <JP>","series":"formulate amelti","shade":"8Ap","type":"color","catalogNo":"","price":580,"barcodeCount":1,"barcode":"4545228269106","flag":0,"shadeDesc":""},{"id":"e4659129-1071-11ee-a2b7-6045bd925463","brand":"PIACELABO <JP>","series":"formulate amelti","shade":"8B","type":"color","catalogNo":"","price":580,"barcodeCount":1,"barcode":"4545228268062","flag":0,"shadeDesc":""},{"id":"e46590cd-1071-11ee-a2b7-6045bd925463","brand":"PIACELABO <JP>","series":"formulate amelti","shade":"8BA","type":"color","catalogNo":"","price":580,"barcodeCount":1,"barcode":"4545228311638","flag":0,"shadeDesc":""},{"id":"e4659068-1071-11ee-a2b7-6045bd925463","brand":"PIACELABO <JP>","series":"formulate amelti","shade":"8BCo","type":"color","catalogNo":"","price":580,"barcodeCount":1,"barcode":"4545228311249","flag":0,"shadeDesc":""},{"id":"e465900d-1071-11ee-a2b7-6045bd925463","brand":"PIACELABO <JP>","series":"formulate amelti","shade":"8Be","type":"color","catalogNo":"","price":580,"barcodeCount":1,"barcode":"4545228268383","flag":0,"shadeDesc":""},{"id":"e4658efa-1071-11ee-a2b7-6045bd925463","brand":"PIACELABO <JP>","series":"formulate amelti","shade":"8CA","type":"color","catalogNo":"","price":580,"barcodeCount":1,"barcode":"4545228312055","flag":0,"shadeDesc":""},{"id":"e4658e48-1071-11ee-a2b7-6045bd925463","brand":"PIACELABO <JP>","series":"formulate amelti","shade":"8G","type":"color","catalogNo":"","price":580,"barcodeCount":1,"barcode":"4545228269595","flag":0,"shadeDesc":""},{"id":"e4658cda-1071-11ee-a2b7-6045bd925463","brand":"PIACELABO <JP>","series":"formulate amelti","shade":"8La","type":"color","catalogNo":"","price":580,"barcodeCount":1,"barcode":"4545228271147","flag":0,"shadeDesc":""},{"id":"e4658a96-1071-11ee-a2b7-6045bd925463","brand":"PIACELABO <JP>","series":"formulate amelti","shade":"8N","type":"color","catalogNo":"","price":580,"barcodeCount":1,"barcode":"4545228267324","flag":0,"shadeDesc":""},{"id":"e46589cb-1071-11ee-a2b7-6045bd925463","brand":"PIACELABO <JP>","series":"formulate amelti","shade":"8O","type":"color","catalogNo":"","price":580,"barcodeCount":1,"barcode":"4545228270331","flag":0,"shadeDesc":""},{"id":"e465896a-1071-11ee-a2b7-6045bd925463","brand":"PIACELABO <JP>","series":"formulate amelti","shade":"8P","type":"color","catalogNo":"","price":580,"barcodeCount":1,"barcode":"4545228271543","flag":0,"shadeDesc":""},{"id":"e465880e-1071-11ee-a2b7-6045bd925463","brand":"PIACELABO <JP>","series":"formulate amelti","shade":"8R","type":"color","catalogNo":"","price":580,"barcodeCount":1,"barcode":"4545228268772","flag":0,"shadeDesc":""},{"id":"e4658228-1071-11ee-a2b7-6045bd925463","brand":"PIACELABO <JP>","series":"formulate amelti","shade":"9N","type":"color","catalogNo":"","price":580,"barcodeCount":1,"barcode":"4545228267249","flag":0,"shadeDesc":""},{"id":"e46581cd-1071-11ee-a2b7-6045bd925463","brand":"PIACELABO <JP>","series":"formulate amelti","shade":"ASH","type":"color","catalogNo":"","price":580,"barcodeCount":1,"barcode":"4545228280538","flag":0,"shadeDesc":""},{"id":"e4657f9c-1071-11ee-a2b7-6045bd925463","brand":"PIACELABO <JP>","series":"formulate amelti","shade":"CL","type":"color","catalogNo":"","price":580,"barcodeCount":1,"barcode":"4545228280774","flag":0,"shadeDesc":""},{"id":"e4657a7e-1071-11ee-a2b7-6045bd925463","brand":"PIACELABO <JP>","series":"formulate amelti","shade":"MAT","type":"color","catalogNo":"","price":580,"barcodeCount":1,"barcode":"4545228280453","flag":0,"shadeDesc":""},{"id":"e4657928-1071-11ee-a2b7-6045bd925463","brand":"PIACELABO <JP>","series":"formulate amelti","shade":"ORANGE","type":"color","catalogNo":"","price":580,"barcodeCount":1,"barcode":"4545228280217","flag":0,"shadeDesc":""},{"id":"e46576e0-1071-11ee-a2b7-6045bd925463","brand":"PIACELABO <JP>","series":"formulate amelti","shade":"P-4N","type":"color","catalogNo":"","price":580,"barcodeCount":1,"barcode":"4545228271932","flag":0,"shadeDesc":""},{"id":"e465767f-1071-11ee-a2b7-6045bd925463","brand":"PIACELABO <JP>","series":"formulate amelti","shade":"P-6A","type":"color","catalogNo":"","price":580,"barcodeCount":1,"barcode":"4545228273561","flag":0,"shadeDesc":""},{"id":"e4657621-1071-11ee-a2b7-6045bd925463","brand":"PIACELABO <JP>","series":"formulate amelti","shade":"P-6BA","type":"color","catalogNo":"","price":580,"barcodeCount":1,"barcode":"4545228312918","flag":0,"shadeDesc":""},{"id":"e46575c4-1071-11ee-a2b7-6045bd925463","brand":"PIACELABO <JP>","series":"formulate amelti","shade":"P-6Co","type":"color","catalogNo":"","price":580,"barcodeCount":1,"barcode":"4545228312765","flag":0,"shadeDesc":""},{"id":"e4657562-1071-11ee-a2b7-6045bd925463","brand":"PIACELABO <JP>","series":"formulate amelti","shade":"P-6La","type":"color","catalogNo":"","price":580,"barcodeCount":1,"barcode":"4545228273714","flag":0,"shadeDesc":""},{"id":"e4657503-1071-11ee-a2b7-6045bd925463","brand":"PIACELABO <JP>","series":"formulate amelti","shade":"P-6N","type":"color","catalogNo":"","price":580,"barcodeCount":1,"barcode":"4545228271857","flag":0,"shadeDesc":""},{"id":"e46574ab-1071-11ee-a2b7-6045bd925463","brand":"PIACELABO <JP>","series":"formulate amelti","shade":"P-8A","type":"color","catalogNo":"","price":580,"barcodeCount":1,"barcode":"4545228273493","flag":0,"shadeDesc":""},{"id":"e4657456-1071-11ee-a2b7-6045bd925463","brand":"PIACELABO <JP>","series":"formulate amelti","shade":"P-8BA","type":"color","catalogNo":"","price":580,"barcodeCount":1,"barcode":"4545228312840","flag":0,"shadeDesc":""},{"id":"e46573f8-1071-11ee-a2b7-6045bd925463","brand":"PIACELABO <JP>","series":"formulate amelti","shade":"P-8Co","type":"color","catalogNo":"","price":580,"barcodeCount":1,"barcode":"4545228312697","flag":0,"shadeDesc":""},{"id":"e465739c-1071-11ee-a2b7-6045bd925463","brand":"PIACELABO <JP>","series":"formulate amelti","shade":"P-8La","type":"color","catalogNo":"","price":580,"barcodeCount":1,"barcode":"4545228273646","flag":0,"shadeDesc":""},{"id":"e465733c-1071-11ee-a2b7-6045bd925463","brand":"PIACELABO <JP>","series":"formulate amelti","shade":"P-8N","type":"color","catalogNo":"","price":580,"barcodeCount":1,"barcode":"4545228271789","flag":0,"shadeDesc":""},{"id":"e46572d8-1071-11ee-a2b7-6045bd925463","brand":"PIACELABO <JP>","series":"formulate amelti","shade":"P-8O","type":"color","catalogNo":"","price":580,"barcodeCount":1,"barcode":"4545228273240","flag":0,"shadeDesc":""},{"id":"e4657278-1071-11ee-a2b7-6045bd925463","brand":"PIACELABO <JP>","series":"formulate amelti","shade":"P-CL","type":"color","catalogNo":"","price":580,"barcodeCount":1,"barcode":"4545228280842","flag":0,"shadeDesc":""},{"id":"e4657166-1071-11ee-a2b7-6045bd925463","brand":"PIACELABO <JP>","series":"formulate amelti","shade":"RED","type":"color","catalogNo":"","price":580,"barcodeCount":1,"barcode":"4545228280149","flag":0,"shadeDesc":""},{"id":"e465709d-1071-11ee-a2b7-6045bd925463","brand":"PIACELABO <JP>","series":"formulate amelti","shade":"VIOLET","type":"color","catalogNo":"","price":580,"barcodeCount":1,"barcode":"4545228280606","flag":0,"shadeDesc":""},{"id":"e4657f3d-1071-11ee-a2b7-6045bd925463","brand":"PIACELABO <JP>","series":"formulate amelti  dressy line","shade":"D-10DM","type":"color","catalogNo":"","price":580,"barcodeCount":1,"barcode":"4545228423584","flag":0,"shadeDesc":""},{"id":"e4657edf-1071-11ee-a2b7-6045bd925463","brand":"PIACELABO <JP>","series":"formulate amelti  dressy line","shade":"D-6DM","type":"color","catalogNo":"","price":580,"barcodeCount":1,"barcode":"4545228423737","flag":0,"shadeDesc":""},{"id":"e4657e80-1071-11ee-a2b7-6045bd925463","brand":"PIACELABO <JP>","series":"formulate amelti  dressy line","shade":"D-8DM","type":"color","catalogNo":"","price":580,"barcodeCount":1,"barcode":"4545228423652","flag":0,"shadeDesc":""},{"id":"e465bc10-1071-11ee-a2b7-6045bd925463","brand":"PIACELABO <JP>","series":"formulate φ","shade":"10A","type":"color","catalogNo":"","price":900,"barcodeCount":1,"barcode":"4545228465140","flag":0,"shadeDesc":""},{"id":"e465b99d-1071-11ee-a2b7-6045bd925463","brand":"PIACELABO <JP>","series":"formulate φ","shade":"10C","type":"color","catalogNo":"","price":900,"barcodeCount":1,"barcode":"4545228464563","flag":0,"shadeDesc":""},{"id":"e465b78e-1071-11ee-a2b7-6045bd925463","brand":"PIACELABO <JP>","series":"formulate φ","shade":"10M","type":"color","catalogNo":"","price":900,"barcodeCount":1,"barcode":"4545228464952","flag":0,"shadeDesc":""},{"id":"e465b721-1071-11ee-a2b7-6045bd925463","brand":"PIACELABO <JP>","series":"formulate φ","shade":"10MC","type":"color","catalogNo":"","price":900,"barcodeCount":1,"barcode":"4545228102052","flag":0,"shadeDesc":""},{"id":"e465b6b9-1071-11ee-a2b7-6045bd925463","brand":"PIACELABO <JP>","series":"formulate φ","shade":"10N","type":"color","catalogNo":"","price":900,"barcodeCount":1,"barcode":"4545228463283","flag":0,"shadeDesc":""},{"id":"e465b507-1071-11ee-a2b7-6045bd925463","brand":"PIACELABO <JP>","series":"formulate φ","shade":"10R","type":"color","catalogNo":"","price":900,"barcodeCount":1,"barcode":"4545228464327","flag":0,"shadeDesc":""},{"id":"e465b439-1071-11ee-a2b7-6045bd925463","brand":"PIACELABO <JP>","series":"formulate φ","shade":"10V","type":"color","catalogNo":"","price":900,"barcodeCount":1,"barcode":"4545228465386","flag":0,"shadeDesc":""},{"id":"e465b37c-1071-11ee-a2b7-6045bd925463","brand":"PIACELABO <JP>","series":"formulate φ","shade":"10Y","type":"color","catalogNo":"","price":900,"barcodeCount":1,"barcode":"4545228464716","flag":0,"shadeDesc":""},{"id":"e465adb7-1071-11ee-a2b7-6045bd925463","brand":"PIACELABO <JP>","series":"formulate φ","shade":"14N","type":"color","catalogNo":"","price":900,"barcodeCount":1,"barcode":"4545228463115","flag":0,"shadeDesc":""},{"id":"e465ac9e-1071-11ee-a2b7-6045bd925463","brand":"PIACELABO <JP>","series":"formulate φ","shade":"2SB","type":"color","catalogNo":"","price":900,"barcodeCount":1,"barcode":"4545228102144","flag":0,"shadeDesc":""},{"id":"e465ac3f-1071-11ee-a2b7-6045bd925463","brand":"PIACELABO <JP>","series":"formulate φ","shade":"4B","type":"color","catalogNo":"","price":900,"barcodeCount":1,"barcode":"4545228464242","flag":0,"shadeDesc":""},{"id":"e465aa6e-1071-11ee-a2b7-6045bd925463","brand":"PIACELABO <JP>","series":"formulate φ","shade":"5B","type":"color","catalogNo":"","price":900,"barcodeCount":1,"barcode":"4545228464174","flag":0,"shadeDesc":""},{"id":"e465a667-1071-11ee-a2b7-6045bd925463","brand":"PIACELABO <JP>","series":"formulate φ","shade":"5SB","type":"color","catalogNo":"","price":900,"barcodeCount":1,"barcode":"4545228102137","flag":0,"shadeDesc":""},{"id":"e465a609-1071-11ee-a2b7-6045bd925463","brand":"PIACELABO <JP>","series":"formulate φ","shade":"6A","type":"color","catalogNo":"","price":900,"barcodeCount":1,"barcode":"4545228465218","flag":0,"shadeDesc":""},{"id":"e465a3a4-1071-11ee-a2b7-6045bd925463","brand":"PIACELABO <JP>","series":"formulate φ","shade":"6B","type":"color","catalogNo":"","price":900,"barcodeCount":1,"barcode":"4545228464006","flag":0,"shadeDesc":""},{"id":"e465a1d7-1071-11ee-a2b7-6045bd925463","brand":"PIACELABO <JP>","series":"formulate φ","shade":"6C","type":"color","catalogNo":"","price":900,"barcodeCount":1,"barcode":"4545228464648","flag":0,"shadeDesc":""},{"id":"e4659e92-1071-11ee-a2b7-6045bd925463","brand":"PIACELABO <JP>","series":"formulate φ","shade":"6M","type":"color","catalogNo":"","price":900,"barcodeCount":1,"barcode":"4545228465065","flag":0,"shadeDesc":""},{"id":"e4659e39-1071-11ee-a2b7-6045bd925463","brand":"PIACELABO <JP>","series":"formulate φ","shade":"6MC","type":"color","catalogNo":"","price":900,"barcodeCount":1,"barcode":"4545228102069","flag":0,"shadeDesc":""},{"id":"e4659d80-1071-11ee-a2b7-6045bd925463","brand":"PIACELABO <JP>","series":"formulate φ","shade":"6N","type":"color","catalogNo":"","price":900,"barcodeCount":1,"barcode":"4545228463740","flag":0,"shadeDesc":""},{"id":"e4659ba6-1071-11ee-a2b7-6045bd925463","brand":"PIACELABO <JP>","series":"formulate φ","shade":"6R","type":"color","catalogNo":"","price":900,"barcodeCount":1,"barcode":"4545228464495","flag":0,"shadeDesc":""},{"id":"e4659a97-1071-11ee-a2b7-6045bd925463","brand":"PIACELABO <JP>","series":"formulate φ","shade":"6SB","type":"color","catalogNo":"","price":900,"barcodeCount":1,"barcode":"4545228102120","flag":0,"shadeDesc":""},{"id":"e4659a3a-1071-11ee-a2b7-6045bd925463","brand":"PIACELABO <JP>","series":"formulate φ","shade":"6V","type":"color","catalogNo":"","price":900,"barcodeCount":1,"barcode":"4545228465454","flag":0,"shadeDesc":""},{"id":"e46599de-1071-11ee-a2b7-6045bd925463","brand":"PIACELABO <JP>","series":"formulate φ","shade":"6Y","type":"color","catalogNo":"","price":900,"barcodeCount":1,"barcode":"4545228464884","flag":0,"shadeDesc":""},{"id":"e46598c3-1071-11ee-a2b7-6045bd925463","brand":"PIACELABO <JP>","series":"formulate φ","shade":"7B","type":"color","catalogNo":"","price":900,"barcodeCount":1,"barcode":"4545228463993","flag":0,"shadeDesc":""},{"id":"e46595df-1071-11ee-a2b7-6045bd925463","brand":"PIACELABO <JP>","series":"formulate φ","shade":"7N","type":"color","catalogNo":"","price":900,"barcodeCount":1,"barcode":"4545228463672","flag":0,"shadeDesc":""},{"id":"e465946a-1071-11ee-a2b7-6045bd925463","brand":"PIACELABO <JP>","series":"formulate φ","shade":"7SB","type":"color","catalogNo":"","price":900,"barcodeCount":1,"barcode":"4545228102113","flag":0,"shadeDesc":""},{"id":"e4659404-1071-11ee-a2b7-6045bd925463","brand":"PIACELABO <JP>","series":"formulate φ","shade":"8A","type":"color","catalogNo":"","price":900,"barcodeCount":1,"barcode":"4545228110798","flag":0,"shadeDesc":""},{"id":"e4659186-1071-11ee-a2b7-6045bd925463","brand":"PIACELABO <JP>","series":"formulate φ","shade":"8B","type":"color","catalogNo":"","price":900,"barcodeCount":1,"barcode":"4545228463825","flag":0,"shadeDesc":""},{"id":"e4658f50-1071-11ee-a2b7-6045bd925463","brand":"PIACELABO <JP>","series":"formulate φ","shade":"8C","type":"color","catalogNo":"","price":900,"barcodeCount":1,"barcode":"4545228110750","flag":0,"shadeDesc":""},{"id":"e4658c21-1071-11ee-a2b7-6045bd925463","brand":"PIACELABO <JP>","series":"formulate φ","shade":"8M","type":"color","catalogNo":"","price":900,"barcodeCount":1,"barcode":"4545228110781","flag":0,"shadeDesc":""},{"id":"e4658bc2-1071-11ee-a2b7-6045bd925463","brand":"PIACELABO <JP>","series":"formulate φ","shade":"8MC","type":"color","catalogNo":"","price":900,"barcodeCount":1,"barcode":"4545228110811","flag":0,"shadeDesc":""},{"id":"e4658af9-1071-11ee-a2b7-6045bd925463","brand":"PIACELABO <JP>","series":"formulate φ","shade":"8N","type":"color","catalogNo":"","price":900,"barcodeCount":1,"barcode":"4545228463504","flag":0,"shadeDesc":""},{"id":"e465888b-1071-11ee-a2b7-6045bd925463","brand":"PIACELABO <JP>","series":"formulate φ","shade":"8R","type":"color","catalogNo":"","price":900,"barcodeCount":1,"barcode":"4545228110736","flag":0,"shadeDesc":""},{"id":"e46583ab-1071-11ee-a2b7-6045bd925463","brand":"PIACELABO <JP>","series":"formulate φ","shade":"8SB","type":"color","catalogNo":"","price":900,"barcodeCount":1,"barcode":"4545228102090","flag":0,"shadeDesc":""},{"id":"e465834b-1071-11ee-a2b7-6045bd925463","brand":"PIACELABO <JP>","series":"formulate φ","shade":"8V","type":"color","catalogNo":"","price":900,"barcodeCount":1,"barcode":"4545228110804","flag":0,"shadeDesc":""},{"id":"e46582ec-1071-11ee-a2b7-6045bd925463","brand":"PIACELABO <JP>","series":"formulate φ","shade":"8Y","type":"color","catalogNo":"","price":900,"barcodeCount":1,"barcode":"4545228110774","flag":0,"shadeDesc":""},{"id":"e465828b-1071-11ee-a2b7-6045bd925463","brand":"PIACELABO <JP>","series":"formulate φ","shade":"9N","type":"color","catalogNo":"","price":900,"barcodeCount":1,"barcode":"4545228463351","flag":0,"shadeDesc":""},{"id":"e4657ff7-1071-11ee-a2b7-6045bd925463","brand":"PIACELABO <JP>","series":"formulate φ","shade":"CL","type":"color","catalogNo":"","price":900,"barcodeCount":1,"barcode":"4545228465539","flag":0,"shadeDesc":""},{"id":"e46577a8-1071-11ee-a2b7-6045bd925463","brand":"PIACELABO <JP>","series":"formulate φ","shade":"OX3% 1000ml","type":"developer","catalogNo":"","price":1200,"barcodeCount":1,"barcode":"4545228465775","flag":0,"shadeDesc":""},{"id":"e4657745-1071-11ee-a2b7-6045bd925463","brand":"PIACELABO <JP>","series":"formulate φ","shade":"OX6% 1000ml","type":"developer","catalogNo":"","price":1200,"barcodeCount":1,"barcode":"4545228465607","flag":0,"shadeDesc":""},{"id":"e4658110-1071-11ee-a2b7-6045bd925463","brand":"PIACELABO <JP>","series":"HAIR MAKE COLOR RESHADE","shade":"BK","type":"color","catalogNo":"","price":800,"barcodeCount":1,"barcode":"4545228305620","flag":0,"shadeDesc":""},{"id":"e4658053-1071-11ee-a2b7-6045bd925463","brand":"PIACELABO <JP>","series":"HAIR MAKE COLOR RESHADE","shade":"CL","type":"color","catalogNo":"","price":800,"barcodeCount":1,"barcode":"4545228305477","flag":0,"shadeDesc":""},{"id":"e4657e1d-1071-11ee-a2b7-6045bd925463","brand":"PIACELABO <JP>","series":"HAIR MAKE COLOR RESHADE","shade":"D-NB","type":"color","catalogNo":"","price":800,"barcodeCount":1,"barcode":"4545228305934","flag":0,"shadeDesc":""},{"id":"e4657dbf-1071-11ee-a2b7-6045bd925463","brand":"PIACELABO <JP>","series":"HAIR MAKE COLOR RESHADE","shade":"D-OB","type":"color","catalogNo":"","price":800,"barcodeCount":1,"barcode":"4545228306368","flag":0,"shadeDesc":""},{"id":"e4657d66-1071-11ee-a2b7-6045bd925463","brand":"PIACELABO <JP>","series":"HAIR MAKE COLOR RESHADE","shade":"L-NB","type":"color","catalogNo":"","price":800,"barcodeCount":1,"barcode":"4545228305798","flag":0,"shadeDesc":""},{"id":"e4657d10-1071-11ee-a2b7-6045bd925463","brand":"PIACELABO <JP>","series":"HAIR MAKE COLOR RESHADE","shade":"L-OB","type":"color","catalogNo":"","price":800,"barcodeCount":1,"barcode":"4545228306122","flag":0,"shadeDesc":""},{"id":"e4657cb8-1071-11ee-a2b7-6045bd925463","brand":"PIACELABO <JP>","series":"HAIR MAKE COLOR RESHADE","shade":"L-YB","type":"color","catalogNo":"","price":800,"barcodeCount":1,"barcode":"4545228306436","flag":0,"shadeDesc":""},{"id":"e4657c58-1071-11ee-a2b7-6045bd925463","brand":"PIACELABO <JP>","series":"HAIR MAKE COLOR RESHADE","shade":"M-MB","type":"color","catalogNo":"","price":800,"barcodeCount":1,"barcode":"4545228306689","flag":0,"shadeDesc":""},{"id":"e4657bf6-1071-11ee-a2b7-6045bd925463","brand":"PIACELABO <JP>","series":"HAIR MAKE COLOR RESHADE","shade":"M-NB","type":"color","catalogNo":"","price":800,"barcodeCount":1,"barcode":"4545228305866","flag":0,"shadeDesc":""},{"id":"e4657b98-1071-11ee-a2b7-6045bd925463","brand":"PIACELABO <JP>","series":"HAIR MAKE COLOR RESHADE","shade":"M-OB","type":"color","catalogNo":"","price":800,"barcodeCount":1,"barcode":"4545228306290","flag":0,"shadeDesc":""},{"id":"e4657b3c-1071-11ee-a2b7-6045bd925463","brand":"PIACELABO <JP>","series":"HAIR MAKE COLOR RESHADE","shade":"M-RB","type":"color","catalogNo":"","price":800,"barcodeCount":1,"barcode":"4545228306047","flag":0,"shadeDesc":""},{"id":"e4657ada-1071-11ee-a2b7-6045bd925463","brand":"PIACELABO <JP>","series":"HAIR MAKE COLOR RESHADE","shade":"M-YB","type":"color","catalogNo":"","price":800,"barcodeCount":1,"barcode":"4545228306511","flag":0,"shadeDesc":""},{"id":"e4657a20-1071-11ee-a2b7-6045bd925463","brand":"PIACELABO <JP>","series":"HAIR MAKE COLOR RESHADE","shade":"O30","type":"color","catalogNo":"","price":800,"barcodeCount":1,"barcode":"4545228305156","flag":0,"shadeDesc":""},{"id":"e4657984-1071-11ee-a2b7-6045bd925463","brand":"PIACELABO <JP>","series":"HAIR MAKE COLOR RESHADE","shade":"OR20","type":"color","catalogNo":"","price":800,"barcodeCount":1,"barcode":"4545228305088","flag":0,"shadeDesc":""},{"id":"e46571c3-1071-11ee-a2b7-6045bd925463","brand":"PIACELABO <JP>","series":"HAIR MAKE COLOR RESHADE","shade":"R10","type":"color","catalogNo":"","price":800,"barcodeCount":1,"barcode":"4545228304975","flag":0,"shadeDesc":""},{"id":"e4657104-1071-11ee-a2b7-6045bd925463","brand":"PIACELABO <JP>","series":"HAIR MAKE COLOR RESHADE","shade":"RP90","type":"color","catalogNo":"","price":800,"barcodeCount":1,"barcode":"4545228305309","flag":0,"shadeDesc":""},{"id":"e465721d-1071-11ee-a2b7-6045bd925463","brand":"PIACELABO <JP>","series":"PIACELABO","shade":"POWDER BLEACH 200g","type":"bleach","catalogNo":"","price":0,"barcodeCount":1,"barcode":"4545228233930","flag":0,"shadeDesc":""}]
